{
  "resourceType": "StructureDefinition",
  "id": "aslp-paa-moderatetoseverepulmonarydisease-screening-casefeature",
  "meta": {
    "profile": [
      "http://hl7.org/fhir/uv/cpg/StructureDefinition/cpg-publishablecasefeature"
    ]
  },
  "extension": [
    {
      "url": "http://hl7.org/fhir/uv/cpg/StructureDefinition/cpg-knowledgeCapability",
      "valueCode": "shareable"
    },
    {
      "url": "http://hl7.org/fhir/uv/cpg/StructureDefinition/cpg-knowledgeCapability",
      "valueCode": "computable"
    },
    {
      "url": "http://hl7.org/fhir/uv/cpg/StructureDefinition/cpg-knowledgeCapability",
      "valueCode": "executable"
    },
    {
      "url": "http://hl7.org/fhir/uv/cpg/StructureDefinition/cpg-knowledgeCapability",
      "valueCode": "publishable"
    },
    {
      "url" : "http://hl7.org/fhir/uv/cpg/StructureDefinition/cpg-knowledgeRepresentationLevel",
      "valueCode" : "structured"
    },
    {
      "url": "http://hl7.org/fhir/us/cqfmeasures/StructureDefinition/cqfm-softwaresystem",
      "valueReference": {
        "reference": "Device/cqf-tooling"
      }
    },
    {
      "url": "http://hl7.org/fhir/uv/cpg/StructureDefinition/cpg-featureExpression",
      "valueExpression": {
        "language": "text/cql-identifier",
        "expression": "Qualifying Moderate To Severe Pulmonary Disease",
        "reference": "http://example.org/sdh/dtr/aslp/Library/ASLPPolicyPAA"
      }
    }
  ],
  "url": "http://example.org/sdh/dtr/aslp/StructureDefinition/aslp-paa-moderatetoseverepulmonarydisease-screening-casefeature",
  "name": "ModerateToSeverePulmonaryDisease",
  "title": "Moderate To Severe Pulmonary Disease",
  "status": "draft",
  "experimental": true,
  "description": "Moderate To Severe Pulmonary Disease",
  "useContext": [
    {
      "code": {
        "system": "http://terminology.hl7.org/CodeSystem/usage-context-type",
        "code": "task",
        "display": "Workflow Task"
      }
    }
  ],
  "fhirVersion": "4.0.1",
  "kind": "resource",
  "abstract": false,
  "type": "Condition",
  "baseDefinition": "http://hl7.org/fhir/StructureDefinition/Condition",
  "derivation": "constraint",
  "differential": {
    "element": [
      {
        "id": "Condition",
        "path": "Condition",
        "mustSupport": false
      },
      {
        "id": "Condition.code",
        "path": "Condition.code",
        "short": "Qualifying Moderate To Severe Pulmonary Disease",
        "definition": "Qualifying Moderate To Severe Pulmonary Disease",
        "min": 1,
        "max": "1",
        "type": [
          {
            "code": "CodeableConcept"
          }
        ],
        "mustSupport": true,
        "patternCodeableConcept": {
          "coding": [
            {
              "system": "http://example.org/sdh/dtr/aslp/CodeSystem/aslp-paa-screening-codes",
              "code": "Moderate-To-Severe-Pulmonary-Disease",
              "display": "Qualifying Moderate To Severe Pulmonary Disease"
            }
          ]
        }
      },
      {
        "id": "Condition.value[x]",
        "path": "Condition.value[x]",
        "short": "Patient has moderate to severe pulmonary disease?",
        "definition": "Patient has moderate to severe pulmonary disease?",
        "min": 1,
        "max": "1",
        "type": [
          {
            "code": "boolean"
          }
        ],
        "mustSupport": true
      }
    ]
  }
}